{
  "date": "2026年3月23日 08:30",
  "ndx": { "price": "21,648", "change": -2.01 },
  "spx": { "price": "6,486", "change": -1.70 },
  "dji": { "price": "45,577", "change": -0.96 },
  "hsi": { "price": "25,277", "change": -0.88 },
  "hstec": { "price": "4,872", "change": -2.48 },
  "sse": { "price": "4,123", "change": 0.65 },
  "szse": { "price": "14,354", "change": 2.04 },
  "gold": { "price": "$4,674", "change": 1.39 },
  "oil": { "price": "$110", "change": 3.30 },
  "btc": { "price": "$68,951", "change": -2.49 },
  "eth": { "price": "$2,100", "change": -2.51 },
  "macro_summary": "特朗普48小时最后通牒：若霍尔木兹海峡不开放将打击伊朗发电站，伊朗威胁完全关闭海峡并反击美以能源设施。油价创近4年新高，全球滞胀风险急剧升级。",
  "logic_chain": [
    "特朗普48小时最后通牒打击伊朗发电站 → 伊朗威胁完全关闭霍尔木兹 → 油价周一料继续上涨",
    "伊朗导弹击中以色列迪莫纳核设施区域致50+伤 → 以色列空袭德黑兰贝鲁特 → 战争继续升级",
    "油价$110创近4年新高 + 美联储降息无望 → 滞胀格局确立 → 美股承压",
    "BTC从$70,700跌至$68,951 → 避险资产短期承压 → 但机构买盘持续",
    "A股周五反弹（沪指+0.65%至4123）→ 战争结束预期+抄底资金入场 → 但外部风险仍存"
  ],
  "market_analysis": [
    {
      "title": "🇺🇸 美股",
      "status": "bearish",
      "summary": "周五大跌创2026新低，道指跌444点，特朗普48小时通牒加剧市场恐慌",
      "details": [
        "道指跌0.96%至45,577点（-444点）",
        "S&P 500跌1.5%，纳指跌2.01%",
        "英伟达-3.17%领跌科技股",
        "油价$110高位+降息无望确立滞胀",
        "周一料继续承压，战争升级风险高"
      ],
      "catalyst": "特朗普48小时通牒+伊朗威胁完全关闭霍尔木兹海峡+能源设施互相威胁",
      "next_watch": "S&P 6,400关键支撑；周一期货低开风险"
    },
    {
      "title": "🇭🇰 港股",
      "status": "neutral",
      "summary": "周五跟跌美股，恒指收25,277，科技股承压",
      "details": [
        "恒指跌0.88%至25,277点",
        "恒生科技跌2.48%至4,872点",
        "科技股跟随美股纳指联动下跌",
        "北水仍有净买入显示资金底部承接",
        "周一视美股期货及战局走向"
      ],
      "catalyst": "美股暴跌传导+地缘风险溢价+油价高企",
      "next_watch": "25,000心理支撑；美股若继续跌将联动"
    },
    {
      "title": "🇨🇳 A股",
      "status": "neutral",
      "summary": "周五逆势反弹，沪指收复4100点，深证涨2%，市场押注战争即将结束",
      "details": [
        "沪指涨0.65%至4,123点",
        "深证综指涨2.04%至14,354点",
        "特朗普称军事行动即将结束提振信心",
        "创业板结构性行情持续",
        "成交量放大显示抄底资金入场"
      ],
      "catalyst": "战争即将结束预期+政策托底信号+抄底资金涌入",
      "next_watch": "4,000支撑确认；关注周末战局变化"
    },
    {
      "title": "🥇 黄金",
      "status": "neutral",
      "summary": "企稳$4,674，本周从$5,000暴跌17%后有所企稳",
      "details": [
        "现货金约$4,674/盎司",
        "较周中$5,000高点跌约17%",
        "$4,600-$4,760区间震荡",
        "避险需求与获利回吐博弈",
        "战争升级可能再推高金价"
      ],
      "catalyst": "冲破$5,000后技术性回调+获利盘涌出+战争不确定性",
      "next_watch": "$4,600支撑/$4,800阻力；战争走向决定方向"
    },
    {
      "title": "🛢️ 原油",
      "status": "bullish",
      "summary": "Brent收$110创近4年新高，周一料继续上涨",
      "details": [
        "Brent原油$110/桶附近",
        "路透社：周一料继续上涨",
        "特朗普威胁打击伊朗发电站",
        "伊朗威胁完全关闭霍尔木兹海峡",
        "伊朗导弹击中迪莫纳致50+伤"
      ],
      "catalyst": "能源设施互相威胁+霍尔木兹海峡危机+战争持续升级",
      "next_watch": "若霍尔木兹完全关闭油价或破$120"
    },
    {
      "title": "₿ 加密货币",
      "status": "bearish",
      "summary": "BTC跌破$69,000至$68,951，避险资产短期承压",
      "details": [
        "BTC报$68,951（-2.49%）",
        "ETH约$2,100（-2.51%）",
        "较周中$70,700下跌约2.5%",
        "风险资产抛售蔓延至加密市场",
        "但机构ETF买盘仍在持续"
      ],
      "catalyst": "美股暴跌传导+风险偏好下降+地缘不确定性",
      "next_watch": "$68,000支撑/$72,000阻力"
    }
  ],
  "us_market_preview": {
    "title": "📊 本周展望（3/23-28）",
    "summary": "特朗普48小时通牒到期日周一/周二，伊朗威胁完全关闭霍尔木兹海峡。若升级为能源设施攻击，油价恐破$120。",
    "factors": [
      "特朗普48小时最后通牒：打击伊朗发电站（周一到期）",
      "伊朗威胁：完全关闭霍尔木兹海峡+打击美以盟友能源设施",
      "伊朗导弹击中以色列迪莫纳核设施区域致50+伤",
      "以色列周五再度空袭德黑兰和贝鲁特",
      "下周关注：PCE通胀数据、美联储官员讲话"
    ],
    "scenarios": [
      {
        "condition": "霍尔木兹重新开放 / 停火谈判启动",
        "prediction": "油价回落至$95-100，美股超跌反弹3-5%",
        "probability": "10%"
      },
      {
        "condition": "维持现状，双方口头威胁但不升级攻击",
        "prediction": "美股震荡下行6,300-6,500区间",
        "probability": "40%"
      },
      {
        "condition": "能源设施攻击爆发 / 霍尔木兹完全关闭",
        "prediction": "油价破$120，美股加速下跌测试6,000",
        "probability": "50%"
      }
    ]
  },
  "advice": {
    "summary": "48小时通牒到期在即，能源设施互相威胁为近期最高风险。宜高现金/防守配置，等待明确信号。",
    "positions": [
      {
        "asset": "美股",
        "action": "减仓/观望",
        "reasoning": "48小时通牒到期风险极高，油价若破$120将加速下跌",
        "level": "S&P 6,300支撑"
      },
      {
        "asset": "港股",
        "action": "观望",
        "reasoning": "美股联动+地缘风险，等待美股企稳",
        "level": "恒指25,000支撑"
      },
      {
        "asset": "A股",
        "action": "轻仓持有",
        "reasoning": "周五反弹显示韧性，但外部风险仍存",
        "level": "沪指4,000支撑"
      },
      {
        "asset": "黄金",
        "action": "持有/小幅加仓",
        "reasoning": "若战争升级避险需求将重新推高金价",
        "level": "$4,600支撑"
      },
      {
        "asset": "原油",
        "action": "谨慎观望",
        "reasoning": "$110高位波动巨大，不宜追高做多",
        "level": "$100-120区间"
      },
      {
        "asset": "BTC",
        "action": "观望",
        "reasoning": "短期跟随风险资产下跌，等待企稳",
        "level": "$68,000支撑"
      }
    ],
    "risks": [
      "48小时通牒到期后美国攻击伊朗发电站触发全面战争",
      "伊朗完全关闭霍尔木兹海峡引发全球能源危机",
      "油价突破$120引发全球经济衰退恐慌",
      "以色列核设施受损引发更大规模报复"
    ]
  },
  "updated_at": "2026-03-23T08:30:00+08:00"
}
