{
  "date": "2026年3月13日 08:30",
  "ndx": { "price": "22,312", "change": -1.78 },
  "spx": { "price": "6,673", "change": -1.52 },
  "dji": { "price": "46,678", "change": -1.56 },
  "hsi": { "price": "25,580", "change": -1.23 },
  "hstec": { "price": "4,850", "change": -1.50 },
  "sse": { "price": "4,140", "change": 0.15 },
  "szse": { "price": "14,520", "change": 0.38 },
  "gold": { "price": "$5,156", "change": -0.39 },
  "oil": { "price": "$100.20", "change": 16.00 },
  "btc": { "price": "$70,242", "change": 0.04 },
  "eth": { "price": "$2,050", "change": -0.80 },
  "macro_summary": "波斯湾局势急剧升级，布伦特原油突破$100/桶，全球股市遭重挫。美股三大指数跌超1.5%，港股跌1.2%，仅A股逆势微涨。黄金从$5,238高位回落，BTC企稳$70K。市场进入避险模式。",
  "logic_chain": [
    "伊朗新任最高领袖强硬表态 → 波斯湾紧张局势升级 → 布伦特原油飙升至$100+",
    "油价暴涨 → 通胀预期上升 → 美联储降息预期降温 → 美股连跌三日",
    "地缘风险升温 → 资金涌入避险资产 → 黄金盘中创$5,238新高",
    "A股相对独立 → 油化工板块大涨 → 沪指逆势收涨0.15%"
  ],
  "market_analysis": [
    {
      "title": "🇺🇸 美股",
      "status": "bearish",
      "summary": "连跌三日，地缘危机主导市场",
      "details": [
        "道指跌739点(-1.56%)报46,678",
        "标普500跌1.52%报6,673",
        "纳指跌1.78%报22,312",
        "Russell 2000跌1.51%，小盘股承压"
      ],
      "catalyst": "伊朗新任最高领袖强硬言论引发波斯湾危机，油价逼近$100",
      "next_watch": "波斯湾局势演变，关注霍尔木兹海峡航运安全"
    },
    {
      "title": "🇭🇰 港股",
      "status": "bearish",
      "summary": "跟随外围下挫，全线下跌",
      "details": [
        "恒生指数跌1.23%报25,580",
        "房地产、金融板块跌超1%",
        "国泰航空逆势上涨",
        "农夫山泉、中国神华领跌"
      ],
      "catalyst": "外围风险偏好急剧下降，资金流出港股",
      "next_watch": "25,000心理关口支撑，若跌破或加速调整"
    },
    {
      "title": "🇨🇳 A股",
      "status": "bullish",
      "summary": "逆势微涨，油化工板块领涨",
      "details": [
        "上证指数涨0.15%报4,140",
        "油气化工板块大涨（油价利好）",
        "科技股回调整理",
        "大唐发电涨停、三安光电涨停"
      ],
      "catalyst": "油价暴涨利好能源股，A股相对独立于外围市场",
      "next_watch": "沪指能否突破4,150阻力，科技股企稳信号"
    },
    {
      "title": "🥇 黄金",
      "status": "bullish",
      "summary": "盘中创新高后回落，避险需求强劲",
      "details": [
        "现货金报$5,156，盘中最高$5,238",
        "日跌0.39%，回吐部分涨幅",
        "CPI数据提振美元，黄金承压"
      ],
      "catalyst": "地缘风险推升避险买盘，但CPI数据令美元走强形成压制",
      "next_watch": "$5,100支撑 / $5,250阻力"
    },
    {
      "title": "₿ 加密货币",
      "status": "neutral",
      "summary": "BTC企稳$70K，震荡整理",
      "details": [
        "BTC报$70,242，24h微涨",
        "市值约1.41万亿美元",
        "ETH约$2,050，微跌0.8%",
        "震荡指标显示中性信号"
      ],
      "catalyst": "风险资产整体承压，但BTC展现一定韧性",
      "next_watch": "BTC $68,000关键支撑，$72,000阻力"
    },
    {
      "title": "🛢️ 原油",
      "status": "bullish",
      "summary": "地缘危机推动油价飙升至$100",
      "details": [
        "布伦特原油突破$100/桶",
        "单日涨幅超16%",
        "霍尔木兹海峡供应担忧加剧"
      ],
      "catalyst": "伊朗强硬表态引发市场对中东供应中断的恐慌",
      "next_watch": "伊朗后续行动，$100关口能否站稳"
    }
  ],
  "advice": {
    "summary": "地缘风险主导短期行情，建议降低风险敞口，增配避险资产，A股能源股可短线关注。",
    "positions": [
      {
        "asset": "A股",
        "action": "持有",
        "reasoning": "相对独立于外围，能源股受益于油价上涨",
        "level": "沪指4,100支撑 / 4,150阻力"
      },
      {
        "asset": "港股",
        "action": "减仓",
        "reasoning": "外围风险敞口大，短期承压",
        "level": "恒指25,000支撑"
      },
      {
        "asset": "美股",
        "action": "观望",
        "reasoning": "地缘不确定性高，等待局势明朗",
        "level": "标普6,500支撑"
      },
      {
        "asset": "黄金",
        "action": "持有/加仓",
        "reasoning": "避险需求强劲，逢回调可加仓",
        "level": "$5,100支撑 / $5,250阻力"
      },
      {
        "asset": "BTC",
        "action": "观望",
        "reasoning": "宏观不确定性下表现韧性，但需等待方向确认",
        "level": "$68,000关键支撑"
      }
    ],
    "risks": [
      "伊朗局势进一步升级可能导致霍尔木兹海峡封锁",
      "油价持续高企将重燃通胀担忧，美联储或延迟降息",
      "若标普跌破6,500可能引发技术性抛售"
    ]
  },
  "updated_at": "2026-03-13T08:30:00+08:00"
}
