{"status":"ok","api_version":"v2.6","api_status":"active","lang":"zh_CN","unit":"metric","tzshift":28800,"timezone":"Asia/Shanghai","server_time":1772991851,"location":[31.123,121.405],"result":{"realtime":{"status":"ok","temperature":6.75,"humidity":0.78,"cloudrate":1.0,"skycon":"CLOUDY","visibility":13.46,"dswrf":0.0,"wind":{"speed":2.85,"direction":71.57},"pressure":102626.44,"apparent_temperature":5.3,"precipitation":{"local":{"status":"ok","datasource":"radar","intensity":0.0},"nearest":{"status":"ok","distance":212.85,"intensity":0.1875}},"air_quality":{"pm25":12,"pm10":23,"o3":76,"so2":6,"no2":13,"co":0.6,"aqi":{"chn":24,"usa":65},"description":{"chn":"优","usa":"良"}},"life_index":{"ultraviolet":{"index":0,"desc":"无"},"comfort":{"index":12,"desc":"湿冷"}}},"hourly":{"status":"ok","description":"多云，今天晚间22点钟后转晴","precipitation":[{"datetime":"2026-03-09T01:00+08:00","value":0.0,"probability":0},{"datetime":"2026-03-09T02:00+08:00","value":0.0,"probability":0},{"datetime":"2026-03-09T03:00+08:00","value":0.0,"probability":0},{"datetime":"2026-03-09T04:00+08:00","value":0.0,"probability":0},{"datetime":"2026-03-09T05:00+08:00","value":0.0,"probability":0},{"datetime":"2026-03-09T06:00+08:00","value":0.0,"probability":0},{"datetime":"2026-03-09T07:00+08:00","value":0.0,"probability":0},{"datetime":"2026-03-09T08:00+08:00","value":0.0,"probability":0},{"datetime":"2026-03-09T09:00+08:00","value":0.0,"probability":0},{"datetime":"2026-03-09T10:00+08:00","value":0.0,"probability":0},{"datetime":"2026-03-09T11:00+08:00","value":0.0,"probability":0},{"datetime":"2026-03-09T12:00+08:00","value":0.0,"probability":0},{"datetime":"2026-03-09T13:00+08:00","value":0.0,"probability":0},{"datetime":"2026-03-09T14:00+08:00","value":0.0,"probability":0},{"datetime":"2026-03-09T15:00+08:00","value":0.0,"probability":0},{"datetime":"2026-03-09T16:00+08:00","value":0.0,"probability":0},{"datetime":"2026-03-09T17:00+08:00","value":0.0,"probability":0},{"datetime":"2026-03-09T18:00+08:00","value":0.0,"probability":0},{"datetime":"2026-03-09T19:00+08:00","value":0.0,"probability":0},{"datetime":"2026-03-09T20:00+08:00","value":0.0,"probability":0},{"datetime":"2026-03-09T21:00+08:00","value":0.0,"probability":0},{"datetime":"2026-03-09T22:00+08:00","value":0.0,"probability":0},{"datetime":"2026-03-09T23:00+08:00","value":0.0,"probability":0},{"datetime":"2026-03-10T00:00+08:00","value":0.0,"probability":0}],"temperature":[{"datetime":"2026-03-09T01:00+08:00","value":6.75},{"datetime":"2026-03-09T02:00+08:00","value":6.18},{"datetime":"2026-03-09T03:00+08:00","value":6.03},{"datetime":"2026-03-09T04:00+08:00","value":6.33},{"datetime":"2026-03-09T05:00+08:00","value":5.64},{"datetime":"2026-03-09T06:00+08:00","value":5.57},{"datetime":"2026-03-09T07:00+08:00","value":6.17},{"datetime":"2026-03-09T08:00+08:00","value":7.76},{"datetime":"2026-03-09T09:00+08:00","value":9.83},{"datetime":"2026-03-09T10:00+08:00","value":10.95},{"datetime":"2026-03-09T11:00+08:00","value":11.76},{"datetime":"2026-03-09T12:00+08:00","value":12.2},{"datetime":"2026-03-09T13:00+08:00","value":12.63},{"datetime":"2026-03-09T14:00+08:00","value":12.67},{"datetime":"2026-03-09T15:00+08:00","value":12.53},{"datetime":"2026-03-09T16:00+08:00","value":11.85},{"datetime":"2026-03-09T17:00+08:00","value":10.61},{"datetime":"2026-03-09T18:00+08:00","value":9.41},{"datetime":"2026-03-09T19:00+08:00","value":8.39},{"datetime":"2026-03-09T20:00+08:00","value":7.66},{"datetime":"2026-03-09T21:00+08:00","value":7.22},{"datetime":"2026-03-09T22:00+08:00","value":6.89},{"datetime":"2026-03-09T23:00+08:00","value":6.73},{"datetime":"2026-03-10T00:00+08:00","value":6.14}],"apparent_temperature":[{"datetime":"2026-03-09T01:00+08:00","value":5.3},{"datetime":"2026-03-09T02:00+08:00","value":4.8},{"datetime":"2026-03-09T03:00+08:00","value":4.7},{"datetime":"2026-03-09T04:00+08:00","value":5.0},{"datetime":"2026-03-09T05:00+08:00","value":4.2},{"datetime":"2026-03-09T06:00+08:00","value":4.1},{"datetime":"2026-03-09T07:00+08:00","value":4.6},{"datetime":"2026-03-09T08:00+08:00","value":6.0},{"datetime":"2026-03-09T09:00+08:00","value":8.0},{"datetime":"2026-03-09T10:00+08:00","value":8.9},{"datetime":"2026-03-09T11:00+08:00","value":9.5},{"datetime":"2026-03-09T12:00+08:00","value":9.8},{"datetime":"2026-03-09T13:00+08:00","value":10.2},{"datetime":"2026-03-09T14:00+08:00","value":10.3},{"datetime":"2026-03-09T15:00+08:00","value":10.2},{"datetime":"2026-03-09T16:00+08:00","value":9.5},{"datetime":"2026-03-09T17:00+08:00","value":8.2},{"datetime":"2026-03-09T18:00+08:00","value":7.3},{"datetime":"2026-03-09T19:00+08:00","value":6.4},{"datetime":"2026-03-09T20:00+08:00","value":5.6},{"datetime":"2026-03-09T21:00+08:00","value":5.0},{"datetime":"2026-03-09T22:00+08:00","value":4.8},{"datetime":"2026-03-09T23:00+08:00","value":4.5},{"datetime":"2026-03-10T00:00+08:00","value":4.0}],"wind":[{"datetime":"2026-03-09T01:00+08:00","speed":2.85,"direction":71.57},{"datetime":"2026-03-09T02:00+08:00","speed":2.78,"direction":58.78},{"datetime":"2026-03-09T03:00+08:00","speed":2.79,"direction":51.8},{"datetime":"2026-03-09T04:00+08:00","speed":2.83,"direction":47.58},{"datetime":"2026-03-09T05:00+08:00","speed":2.94,"direction":50.46},{"datetime":"2026-03-09T06:00+08:00","speed":3.11,"direction":45.94},{"datetime":"2026-03-09T07:00+08:00","speed":3.62,"direction":41.78},{"datetime":"2026-03-09T08:00+08:00","speed":4.93,"direction":49.44},{"datetime":"2026-03-09T09:00+08:00","speed":5.38,"direction":42.02},{"datetime":"2026-03-09T10:00+08:00","speed":6.42,"direction":39.31},{"datetime":"2026-03-09T11:00+08:00","speed":7.56,"direction":32.55},{"datetime":"2026-03-09T12:00+08:00","speed":8.38,"direction":33.08},{"datetime":"2026-03-09T13:00+08:00","speed":8.24,"direction":30.15},{"datetime":"2026-03-09T14:00+08:00","speed":8.54,"direction":28.19},{"datetime":"2026-03-09T15:00+08:00","speed":8.63,"direction":26.24},{"datetime":"2026-03-09T16:00+08:00","speed":8.64,"direction":22.29},{"datetime":"2026-03-09T17:00+08:00","speed":8.31,"direction":21.34},{"datetime":"2026-03-09T18:00+08:00","speed":6.85,"direction":20.63},{"datetime":"2026-03-09T19:00+08:00","speed":6.19,"direction":18.65},{"datetime":"2026-03-09T20:00+08:00","speed":6.3,"direction":22.17},{"datetime":"2026-03-09T21:00+08:00","speed":6.0,"direction":22.57},{"datetime":"2026-03-09T22:00+08:00","speed":5.11,"direction":23.68},{"datetime":"2026-03-09T23:00+08:00","speed":5.29,"direction":23.25},{"datetime":"2026-03-10T00:00+08:00","speed":4.5,"direction":24.1}],"humidity":[{"datetime":"2026-03-09T01:00+08:00","value":0.78},{"datetime":"2026-03-09T02:00+08:00","value":0.84},{"datetime":"2026-03-09T03:00+08:00","value":0.86},{"datetime":"2026-03-09T04:00+08:00","value":0.87},{"datetime":"2026-03-09T05:00+08:00","value":0.88},{"datetime":"2026-03-09T06:00+08:00","value":0.88},{"datetime":"2026-03-09T07:00+08:00","value":0.82},{"datetime":"2026-03-09T08:00+08:00","value":0.72},{"datetime":"2026-03-09T09:00+08:00","value":0.61},{"datetime":"2026-03-09T10:00+08:00","value":0.54},{"datetime":"2026-03-09T11:00+08:00","value":0.5},{"datetime":"2026-03-09T12:00+08:00","value":0.46},{"datetime":"2026-03-09T13:00+08:00","value":0.44},{"datetime":"2026-03-09T14:00+08:00","value":0.46},{"datetime":"2026-03-09T15:00+08:00","value":0.49},{"datetime":"2026-03-09T16:00+08:00","value":0.53},{"datetime":"2026-03-09T17:00+08:00","value":0.55},{"datetime":"2026-03-09T18:00+08:00","value":0.6},{"datetime":"2026-03-09T19:00+08:00","value":0.66},{"datetime":"2026-03-09T20:00+08:00","value":0.69},{"datetime":"2026-03-09T21:00+08:00","value":0.65},{"datetime":"2026-03-09T22:00+08:00","value":0.61},{"datetime":"2026-03-09T23:00+08:00","value":0.59},{"datetime":"2026-03-10T00:00+08:00","value":0.59}],"cloudrate":[{"datetime":"2026-03-09T01:00+08:00","value":1.0},{"datetime":"2026-03-09T02:00+08:00","value":1.0},{"datetime":"2026-03-09T03:00+08:00","value":0.96},{"datetime":"2026-03-09T04:00+08:00","value":0.14},{"datetime":"2026-03-09T05:00+08:00","value":0.0},{"datetime":"2026-03-09T06:00+08:00","value":0.0},{"datetime":"2026-03-09T07:00+08:00","value":0.0},{"datetime":"2026-03-09T08:00+08:00","value":0.0},{"datetime":"2026-03-09T09:00+08:00","value":0.0},{"datetime":"2026-03-09T10:00+08:00","value":0.0},{"datetime":"2026-03-09T11:00+08:00","value":0.0},{"datetime":"2026-03-09T12:00+08:00","value":0.0},{"datetime":"2026-03-09T13:00+08:00","value":0.35},{"datetime":"2026-03-09T14:00+08:00","value":0.85},{"datetime":"2026-03-09T15:00+08:00","value":0.66},{"datetime":"2026-03-09T16:00+08:00","value":0.94},{"datetime":"2026-03-09T17:00+08:00","value":1.0},{"datetime":"2026-03-09T18:00+08:00","value":1.0},{"datetime":"2026-03-09T19:00+08:00","value":0.87},{"datetime":"2026-03-09T20:00+08:00","value":0.91},{"datetime":"2026-03-09T21:00+08:00","value":0.13},{"datetime":"2026-03-09T22:00+08:00","value":0.0},{"datetime":"2026-03-09T23:00+08:00","value":0.0},{"datetime":"2026-03-10T00:00+08:00","value":0.0}],"skycon":[{"datetime":"2026-03-09T01:00+08:00","value":"FOG"},{"datetime":"2026-03-09T02:00+08:00","value":"FOG"},{"datetime":"2026-03-09T03:00+08:00","value":"FOG"},{"datetime":"2026-03-09T04:00+08:00","value":"CLEAR_NIGHT"},{"datetime":"2026-03-09T05:00+08:00","value":"CLEAR_NIGHT"},{"datetime":"2026-03-09T06:00+08:00","value":"CLEAR_DAY"},{"datetime":"2026-03-09T07:00+08:00","value":"CLEAR_DAY"},{"datetime":"2026-03-09T08:00+08:00","value":"CLEAR_DAY"},{"datetime":"2026-03-09T09:00+08:00","value":"CLEAR_DAY"},{"datetime":"2026-03-09T10:00+08:00","value":"CLEAR_DAY"},{"datetime":"2026-03-09T11:00+08:00","value":"CLEAR_DAY"},{"datetime":"2026-03-09T12:00+08:00","value":"CLEAR_DAY"},{"datetime":"2026-03-09T13:00+08:00","value":"PARTLY_CLOUDY_DAY"},{"datetime":"2026-03-09T14:00+08:00","value":"CLOUDY"},{"datetime":"2026-03-09T15:00+08:00","value":"PARTLY_CLOUDY_DAY"},{"datetime":"2026-03-09T16:00+08:00","value":"CLOUDY"},{"datetime":"2026-03-09T17:00+08:00","value":"FOG"},{"datetime":"2026-03-09T18:00+08:00","value":"FOG"},{"datetime":"2026-03-09T19:00+08:00","value":"CLOUDY"},{"datetime":"2026-03-09T20:00+08:00","value":"CLOUDY"},{"datetime":"2026-03-09T21:00+08:00","value":"CLEAR_NIGHT"},{"datetime":"2026-03-09T22:00+08:00","value":"CLEAR_NIGHT"},{"datetime":"2026-03-09T23:00+08:00","value":"CLEAR_NIGHT"},{"datetime":"2026-03-10T00:00+08:00","value":"CLEAR_NIGHT"}],"pressure":[{"datetime":"2026-03-09T01:00+08:00","value":102626.44},{"datetime":"2026-03-09T02:00+08:00","value":102636.39},{"datetime":"2026-03-09T03:00+08:00","value":102652.46},{"datetime":"2026-03-09T04:00+08:00","value":102663.33},{"datetime":"2026-03-09T05:00+08:00","value":102694.164},{"datetime":"2026-03-09T06:00+08:00","value":102730.625},{"datetime":"2026-03-09T07:00+08:00","value":102811.125},{"datetime":"2026-03-09T08:00+08:00","value":102888.18},{"datetime":"2026-03-09T09:00+08:00","value":102950.79},{"datetime":"2026-03-09T10:00+08:00","value":102946.78},{"datetime":"2026-03-09T11:00+08:00","value":102950.8},{"datetime":"2026-03-09T12:00+08:00","value":102947.99},{"datetime":"2026-03-09T13:00+08:00","value":102921.266},{"datetime":"2026-03-09T14:00+08:00","value":102896.22},{"datetime":"2026-03-09T15:00+08:00","value":102922.82},{"datetime":"2026-03-09T16:00+08:00","value":102931.484},{"datetime":"2026-03-09T17:00+08:00","value":102986.375},{"datetime":"2026-03-09T18:00+08:00","value":103049.07},{"datetime":"2026-03-09T19:00+08:00","value":103096.39},{"datetime":"2026-03-09T20:00+08:00","value":103145.734},{"datetime":"2026-03-09T21:00+08:00","value":103160.695},{"datetime":"2026-03-09T22:00+08:00","value":103175.766},{"datetime":"2026-03-09T23:00+08:00","value":103138.266},{"datetime":"2026-03-10T00:00+08:00","value":103130.59}],"visibility":[{"datetime":"2026-03-09T01:00+08:00","value":13.46},{"datetime":"2026-03-09T02:00+08:00","value":13.31},{"datetime":"2026-03-09T03:00+08:00","value":13.13},{"datetime":"2026-03-09T04:00+08:00","value":12.86},{"datetime":"2026-03-09T05:00+08:00","value":12.5},{"datetime":"2026-03-09T06:00+08:00","value":11.93},{"datetime":"2026-03-09T07:00+08:00","value":12.04},{"datetime":"2026-03-09T08:00+08:00","value":17.16},{"datetime":"2026-03-09T09:00+08:00","value":27.06},{"datetime":"2026-03-09T10:00+08:00","value":35.58},{"datetime":"2026-03-09T11:00+08:00","value":38.52},{"datetime":"2026-03-09T12:00+08:00","value":39.4},{"datetime":"2026-03-09T13:00+08:00","value":40.55},{"datetime":"2026-03-09T14:00+08:00","value":39.28},{"datetime":"2026-03-09T15:00+08:00","value":37.04},{"datetime":"2026-03-09T16:00+08:00","value":34.4},{"datetime":"2026-03-09T17:00+08:00","value":31.38},{"datetime":"2026-03-09T18:00+08:00","value":26.13},{"datetime":"2026-03-09T19:00+08:00","value":20.16},{"datetime":"2026-03-09T20:00+08:00","value":16.25},{"datetime":"2026-03-09T21:00+08:00","value":13.86},{"datetime":"2026-03-09T22:00+08:00","value":13.77},{"datetime":"2026-03-09T23:00+08:00","value":15.46},{"datetime":"2026-03-10T00:00+08:00","value":16.02}],"dswrf":[{"datetime":"2026-03-09T01:00+08:00","value":0.0},{"datetime":"2026-03-09T02:00+08:00","value":0.0},{"datetime":"2026-03-09T03:00+08:00","value":0.0},{"datetime":"2026-03-09T04:00+08:00","value":0.0},{"datetime":"2026-03-09T05:00+08:00","value":0.0},{"datetime":"2026-03-09T06:00+08:00","value":0.0},{"datetime":"2026-03-09T07:00+08:00","value":86.484375},{"datetime":"2026-03-09T08:00+08:00","value":306.34375},{"datetime":"2026-03-09T09:00+08:00","value":525.5781},{"datetime":"2026-03-09T10:00+08:00","value":704.125},{"datetime":"2026-03-09T11:00+08:00","value":824.5469},{"datetime":"2026-03-09T12:00+08:00","value":871.8594},{"datetime":"2026-03-09T13:00+08:00","value":803.3125},{"datetime":"2026-03-09T14:00+08:00","value":753.8125},{"datetime":"2026-03-09T15:00+08:00","value":508.78125},{"datetime":"2026-03-09T16:00+08:00","value":299.09375},{"datetime":"2026-03-09T17:00+08:00","value":121.90625},{"datetime":"2026-03-09T18:00+08:00","value":0.0},{"datetime":"2026-03-09T19:00+08:00","value":0.0},{"datetime":"2026-03-09T20:00+08:00","value":0.0},{"datetime":"2026-03-09T21:00+08:00","value":0.0},{"datetime":"2026-03-09T22:00+08:00","value":0.0},{"datetime":"2026-03-09T23:00+08:00","value":0.0},{"datetime":"2026-03-10T00:00+08:00","value":0.0}],"air_quality":{"aqi":[{"datetime":"2026-03-09T01:00+08:00","value":{"chn":24,"usa":65}},{"datetime":"2026-03-09T02:00+08:00","value":{"chn":23,"usa":54}},{"datetime":"2026-03-09T03:00+08:00","value":{"chn":23,"usa":54}},{"datetime":"2026-03-09T04:00+08:00","value":{"chn":23,"usa":54}},{"datetime":"2026-03-09T05:00+08:00","value":{"chn":23,"usa":54}},{"datetime":"2026-03-09T06:00+08:00","value":{"chn":23,"usa":54}},{"datetime":"2026-03-09T07:00+08:00","value":{"chn":23,"usa":54}},{"datetime":"2026-03-09T08:00+08:00","value":{"chn":24,"usa":54}},{"datetime":"2026-03-09T09:00+08:00","value":{"chn":24,"usa":54}},{"datetime":"2026-03-09T10:00+08:00","value":{"chn":24,"usa":54}},{"datetime":"2026-03-09T11:00+08:00","value":{"chn":26,"usa":54}},{"datetime":"2026-03-09T12:00+08:00","value":{"chn":28,"usa":54}},{"datetime":"2026-03-09T13:00+08:00","value":{"chn":30,"usa":52}},{"datetime":"2026-03-09T14:00+08:00","value":{"chn":32,"usa":52}},{"datetime":"2026-03-09T15:00+08:00","value":{"chn":33,"usa":52}},{"datetime":"2026-03-09T16:00+08:00","value":{"chn":34,"usa":52}},{"datetime":"2026-03-09T17:00+08:00","value":{"chn":34,"usa":52}},{"datetime":"2026-03-09T18:00+08:00","value":{"chn":33,"usa":50}},{"datetime":"2026-03-09T19:00+08:00","value":{"chn":33,"usa":52}},{"datetime":"2026-03-09T20:00+08:00","value":{"chn":32,"usa":52}},{"datetime":"2026-03-09T21:00+08:00","value":{"chn":30,"usa":52}},{"datetime":"2026-03-09T22:00+08:00","value":{"chn":29,"usa":52}},{"datetime":"2026-03-09T23:00+08:00","value":{"chn":28,"usa":50}},{"datetime":"2026-03-10T00:00+08:00","value":{"chn":27,"usa":50}}],"pm25":[{"datetime":"2026-03-09T01:00+08:00","value":12},{"datetime":"2026-03-09T02:00+08:00","value":14},{"datetime":"2026-03-09T03:00+08:00","value":14},{"datetime":"2026-03-09T04:00+08:00","value":14},{"datetime":"2026-03-09T05:00+08:00","value":14},{"datetime":"2026-03-09T06:00+08:00","value":14},{"datetime":"2026-03-09T07:00+08:00","value":14},{"datetime":"2026-03-09T08:00+08:00","value":14},{"datetime":"2026-03-09T09:00+08:00","value":14},{"datetime":"2026-03-09T10:00+08:00","value":14},{"datetime":"2026-03-09T11:00+08:00","value":14},{"datetime":"2026-03-09T12:00+08:00","value":14},{"datetime":"2026-03-09T13:00+08:00","value":13},{"datetime":"2026-03-09T14:00+08:00","value":13},{"datetime":"2026-03-09T15:00+08:00","value":13},{"datetime":"2026-03-09T16:00+08:00","value":13},{"datetime":"2026-03-09T17:00+08:00","value":13},{"datetime":"2026-03-09T18:00+08:00","value":12},{"datetime":"2026-03-09T19:00+08:00","value":13},{"datetime":"2026-03-09T20:00+08:00","value":13},{"datetime":"2026-03-09T21:00+08:00","value":13},{"datetime":"2026-03-09T22:00+08:00","value":13},{"datetime":"2026-03-09T23:00+08:00","value":12},{"datetime":"2026-03-10T00:00+08:00","value":12}]}},"daily":{"status":"ok","astro":[{"date":"2026-03-09T00:00+08:00","sunrise":{"time":"06:11"},"sunset":{"time":"17:58"}},{"date":"2026-03-10T00:00+08:00","sunrise":{"time":"06:10"},"sunset":{"time":"17:58"}},{"date":"2026-03-11T00:00+08:00","sunrise":{"time":"06:09"},"sunset":{"time":"17:59"}}],"precipitation_08h_20h":[{"date":"2026-03-09T00:00+08:00","max":0.0,"min":0.0,"avg":0.0,"probability":0},{"date":"2026-03-10T00:00+08:00","max":0.0,"min":0.0,"avg":0.0,"probability":0},{"date":"2026-03-11T00:00+08:00","max":0.4034,"min":0.0,"avg":0.0381,"probability":60}],"precipitation_20h_32h":[{"date":"2026-03-09T00:00+08:00","max":0.0,"min":0.0,"avg":0.0,"probability":0},{"date":"2026-03-10T00:00+08:00","max":0.0,"min":0.0,"avg":0.0,"probability":0},{"date":"2026-03-11T00:00+08:00","max":0.0,"min":0.0,"avg":0.0,"probability":0}],"precipitation":[{"date":"2026-03-09T00:00+08:00","max":0.0,"min":0.0,"avg":0.0,"probability":0},{"date":"2026-03-10T00:00+08:00","max":0.0,"min":0.0,"avg":0.0,"probability":0},{"date":"2026-03-11T00:00+08:00","max":0.4034,"min":0.0,"avg":0.019,"probability":0}],"temperature":[{"date":"2026-03-09T00:00+08:00","max":12.67,"min":5.57,"avg":8.77},{"date":"2026-03-10T00:00+08:00","max":12.73,"min":3.87,"avg":7.75},{"date":"2026-03-11T00:00+08:00","max":16.25,"min":3.82,"avg":9.23}],"temperature_08h_20h":[{"date":"2026-03-09T00:00+08:00","max":12.67,"min":6.17,"avg":10.7},{"date":"2026-03-10T00:00+08:00","max":12.73,"min":4.62,"avg":10.01},{"date":"2026-03-11T00:00+08:00","max":16.25,"min":5.13,"avg":12.46}],"temperature_20h_32h":[{"date":"2026-03-09T00:00+08:00","max":8.39,"min":3.87,"avg":6.0},{"date":"2026-03-10T00:00+08:00","max":7.65,"min":3.82,"avg":5.04},{"date":"2026-03-11T00:00+08:00","max":9.98,"min":7.27,"avg":8.17}],"wind":[{"date":"2026-03-09T00:00+08:00","max":{"speed":8.64,"direction":22.29},"min":{"speed":2.78,"direction":58.78},"avg":{"speed":5.61,"direction":32.93}},{"date":"2026-03-10T00:00+08:00","max":{"speed":6.09,"direction":124.16},"min":{"speed":2.52,"direction":0.0},"avg":{"speed":4.11,"direction":76.64}},{"date":"2026-03-11T00:00+08:00","max":{"speed":5.4,"direction":106.26},"min":{"speed":2.75,"direction":117.24},"avg":{"speed":3.94,"direction":117.42}}],"wind_08h_20h":[{"date":"2026-03-09T00:00+08:00","max":{"speed":8.64,"direction":22.29},"min":{"speed":3.62,"direction":41.78},"avg":{"speed":7.05,"direction":30.67}},{"date":"2026-03-10T00:00+08:00","max":{"speed":6.09,"direction":124.16},"min":{"speed":2.83,"direction":68.33},"avg":{"speed":3.53,"direction":81.05}},{"date":"2026-03-11T00:00+08:00","max":{"speed":5.4,"direction":106.26},"min":{"speed":3.07,"direction":125.93},"avg":{"speed":3.9,"direction":121.86}}],"wind_20h_32h":[{"date":"2026-03-09T00:00+08:00","max":{"speed":6.3,"direction":22.17},"min":{"speed":2.52,"direction":0.0},"avg":{"speed":4.45,"direction":17.9}},{"date":"2026-03-10T00:00+08:00","max":{"speed":5.65,"direction":118.52},"min":{"speed":2.75,"direction":117.24},"avg":{"speed":3.88,"direction":120.9}},{"date":"2026-03-11T00:00+08:00","max":{"speed":11.19,"direction":36.57},"min":{"speed":3.14,"direction":99.89},"avg":{"speed":8.34,"direction":50.11}}],"humidity":[{"date":"2026-03-09T00:00+08:00","max":0.88,"min":0.44,"avg":0.65},{"date":"2026-03-10T00:00+08:00","max":0.67,"min":0.37,"avg":0.53},{"date":"2026-03-11T00:00+08:00","max":0.84,"min":0.42,"avg":0.64}],"cloudrate":[{"date":"2026-03-09T00:00+08:00","max":1.0,"min":0.0,"avg":0.43},{"date":"2026-03-10T00:00+08:00","max":0.0,"min":0.0,"avg":0.0},{"date":"2026-03-11T00:00+08:00","max":1.0,"min":0.0,"avg":0.55}],"pressure":[{"date":"2026-03-09T00:00+08:00","max":103175.77,"min":102626.44,"avg":102909.7},{"date":"2026-03-10T00:00+08:00","max":103130.59,"min":102465.28,"avg":102796.29},{"date":"2026-03-11T00:00+08:00","max":102466.02,"min":102104.8,"avg":102307.19}],"visibility":[{"date":"2026-03-09T00:00+08:00","max":40.55,"min":11.93,"avg":23.27},{"date":"2026-03-10T00:00+08:00","max":32.4,"min":11.4,"avg":18.73},{"date":"2026-03-11T00:00+08:00","max":24.14,"min":10.76,"avg":23.35}],"dswrf":[{"date":"2026-03-09T00:00+08:00","max":871.9,"min":0.0,"avg":252.4},{"date":"2026-03-10T00:00+08:00","max":915.7,"min":0.0,"avg":269.7},{"date":"2026-03-11T00:00+08:00","max":870.4,"min":0.0,"avg":216.9}],"air_quality":{"aqi":[{"date":"2026-03-09T00:00+08:00","max":{"chn":34,"usa":65},"avg":{"chn":28,"usa":53},"min":{"chn":23,"usa":46}},{"date":"2026-03-10T00:00+08:00","max":{"chn":35,"usa":54},"avg":{"chn":28,"usa":52},"min":{"chn":23,"usa":46}},{"date":"2026-03-11T00:00+08:00","max":{"chn":37,"usa":59},"avg":{"chn":29,"usa":55},"min":{"chn":22,"usa":52}}],"pm25":[{"date":"2026-03-09T00:00+08:00","max":14,"avg":13,"min":11},{"date":"2026-03-10T00:00+08:00","max":14,"avg":13,"min":11},{"date":"2026-03-11T00:00+08:00","max":16,"avg":14,"min":13}]},"skycon":[{"date":"2026-03-09T00:00+08:00","value":"PARTLY_CLOUDY_DAY"},{"date":"2026-03-10T00:00+08:00","value":"CLEAR_DAY"},{"date":"2026-03-11T00:00+08:00","value":"PARTLY_CLOUDY_DAY"}],"skycon_08h_20h":[{"date":"2026-03-09T00:00+08:00","value":"PARTLY_CLOUDY_DAY"},{"date":"2026-03-10T00:00+08:00","value":"CLEAR_DAY"},{"date":"2026-03-11T00:00+08:00","value":"LIGHT_RAIN"}],"skycon_20h_32h":[{"date":"2026-03-09T00:00+08:00","value":"CLEAR_NIGHT"},{"date":"2026-03-10T00:00+08:00","value":"CLEAR_NIGHT"},{"date":"2026-03-11T00:00+08:00","value":"FOG"}],"life_index":{"ultraviolet":[{"date":"2026-03-09T00:00+08:00","index":"2","desc":"弱"},{"date":"2026-03-10T00:00+08:00","index":"2","desc":"弱"},{"date":"2026-03-11T00:00+08:00","index":"2","desc":"弱"}],"carWashing":[{"date":"2026-03-09T00:00+08:00","index":"1","desc":"适宜"},{"date":"2026-03-10T00:00+08:00","index":"3","desc":"较不适宜"},{"date":"2026-03-11T00:00+08:00","index":"3","desc":"较不适宜"}],"dressing":[{"date":"2026-03-09T00:00+08:00","index":"6","desc":"冷"},{"date":"2026-03-10T00:00+08:00","index":"6","desc":"冷"},{"date":"2026-03-11T00:00+08:00","index":"6","desc":"冷"}],"comfort":[{"date":"2026-03-09T00:00+08:00","index":"7","desc":"冷"},{"date":"2026-03-10T00:00+08:00","index":"7","desc":"冷"},{"date":"2026-03-11T00:00+08:00","index":"7","desc":"冷"}],"coldRisk":[{"date":"2026-03-09T00:00+08:00","index":"4","desc":"极易发"},{"date":"2026-03-10T00:00+08:00","index":"4","desc":"极易发"},{"date":"2026-03-11T00:00+08:00","index":"4","desc":"极易发"}]}},"primary":0,"forecast_keypoint":"多云，今天晚间22点钟后转晴"}}